setup.cfg
setup.py
liu_anslagstavlan.egg-info/PKG-INFO
liu_anslagstavlan.egg-info/SOURCES.txt
liu_anslagstavlan.egg-info/dependency_links.txt
liu_anslagstavlan.egg-info/namespace_packages.txt
liu_anslagstavlan.egg-info/not-zip-safe
liu_anslagstavlan.egg-info/requires.txt
liu_anslagstavlan.egg-info/top_level.txt
liuanslagstavlan/__init__.py
liuanslagstavlan/api.py
liuanslagstavlan/config.py
liuanslagstavlan/constants.py
liuanslagstavlan/regex.py
liuanslagstavlan/util.py