Metadata-Version: 1.0
Name: liu-anslagstavlan
Version: 0.9.1-20110113
Summary: Unoffical library for working with the bulletin board of Linköping University.
Home-page: http://github.com/pilt/liu-anslagstavlan
Author: Simon Pantzare
Author-email: simon@pewpewlabs.com
License: BSD
Platform: any
Classifier: Development Status :: 4 - Beta
Classifier: Environment :: Web Environment
Classifier: Intended Audience :: Developers
Classifier: License :: OSI Approved :: BSD License
Classifier: Operating System :: OS Independent
Classifier: Programming Language :: Python
Classifier: Topic :: Internet :: WWW/HTTP :: Dynamic Content
Classifier: Topic :: Software Development :: Libraries :: Python Modules
